osgood/__init__.py
osgood/base.py
osgood-1.3.0.dist-info/LICENSE
osgood-1.3.0.dist-info/METADATA
osgood-1.3.0.dist-info/WHEEL
osgood-1.3.0.dist-info/top_level.txt
osgood-1.3.0.dist-info/RECORD
