Metadata-Version: 2.1
Name: osgood
Version: 1.3.0
Summary: A small collection of useful functions
Author-email: charlesriver456 <osgood.package@gmail.com>
Project-URL: Homepage, https://github.com/charlesriver456/osgood
Project-URL: Bug Tracker, https://github.com/charlesriver456/osgood/issues
Classifier: Programming Language :: Python :: 3
Classifier: License :: OSI Approved :: MIT License
Classifier: Operating System :: OS Independent
Requires-Python: >=3.8
License-File: LICENSE
